memory_master_mind/__init__.py
memory_master_mind/__main__.py
memory_master_mind/app.py
memory_master_mind/assets/math_arithmetic.md
memory_master_mind/assets/mmm_help.md
memory_master_mind/assets/quotes.csv
memory_master_mind/assets/quotes_and_verses.md
memory_master_mind/assets/static_number_sequence.md
memory_master_mind/assets/timed_number_sequence.md
memory_master_mind/components/__init__.py
memory_master_mind/components/challenge_interface.py
memory_master_mind/components/challenge_timer.py
memory_master_mind/components/footer.py
memory_master_mind/components/form_button.py
memory_master_mind/components/form_label.py
memory_master_mind/components/header.py
memory_master_mind/components/home.py
memory_master_mind/components/input_answer.py
memory_master_mind/components/input_text.py
memory_master_mind/components/math_arithmetic.py
memory_master_mind/components/preferences_interface.py
memory_master_mind/components/quotes.py
memory_master_mind/components/show_challenge_interface.py
memory_master_mind/components/static_number_sequence.py
memory_master_mind/components/timed_number_sequence.py
memory_master_mind/db.py
memory_master_mind/runner.py
memory_master_mind/types.py
memory_master_mind-1.0.0.dist-info/entry_points.txt
memory_master_mind-1.0.0.dist-info/LICENSE.txt
memory_master_mind-1.0.0.dist-info/WHEEL
memory_master_mind-1.0.0.dist-info/METADATA
memory_master_mind-1.0.0.dist-info/RECORD
