Metadata-Version: 2.1
Name: memory-master-mind
Version: 1.0.0
Summary: MMM - Memory Master Mind - memory training in the terminal
Home-page: https://github.com/profound-labs/memory-master-mind
License: MIT
Author: Gambhiro
Author-email: profound.labs@gmail.com
Requires-Python: >=3.8,<4.0
Classifier: License :: OSI Approved :: MIT License
Classifier: Programming Language :: Python :: 3
Classifier: Programming Language :: Python :: 3.8
Classifier: Programming Language :: Python :: 3.9
Classifier: Programming Language :: Python :: 3.10
Requires-Dist: appdirs (>=1.4.4,<2.0.0)
Requires-Dist: python-dotenv (>=0.21.0,<0.22.0)
Requires-Dist: textual (>=0.1.18,<0.2.0)
Requires-Dist: typer (>=0.6.1,<0.7.0)
Project-URL: Repository, https://github.com/profound-labs/memory-master-mind
